{
  "annotations": {
    "list": [
      {
        "builtIn": 1,
        "datasource": {
          "type": "grafana",
          "uid": "-- Grafana --"
        },
        "enable": true,
        "hide": true,
        "iconColor": "rgba(0, 211, 255, 1)",
        "name": "Annotations & Alerts",
        "target": {
          "limit": 100,
          "matchAny": false,
          "tags": [],
          "type": "dashboard"
        },
        "type": "dashboard"
      },
      {
        "datasource": {
          "type": "postgres",
          "uid": "te-11s7Vk"
        },
        "enable": false,
        "iconColor": "red",
        "name": "Data Reconstruction Drift Alerts",
        "rawQuery": "SELECT\n  extract(epoch from timestamp) AS time,\n  CASE\n    WHEN value > upper_threshold THEN concat('Upper threshold for ', metric_name, ' crossed')\n    ELSE concat('Lower threshold for ', metric_name, ' crossed')\n  END\n      as text,\n  concat_ws(', ', 'Feature Drift', 'Multivariate Feature Drift', 'Reconstruction Error Drift') as tags\nFROM\n  data_reconstruction_feature_drift_metrics\nWHERE\n  $__timeFilter(timestamp) AND alert is true AND model_id = ${model_id};"
      }
    ]
  },
  "description": "",
  "editable": true,
  "fiscalYearStartMonth": 0,
  "graphTooltip": 0,
  "id": 2,
  "links": [],
  "liveNow": false,
  "panels": [
    {
      "datasource": {
        "type": "postgres",
        "uid": "te-11s7Vk"
      },
      "description": "",
      "fieldConfig": {
        "defaults": {
          "color": {
            "mode": "thresholds"
          },
          "links": [
            {
              "targetBlank": true,
              "title": "Explore in NannyML",
              "url": "http://nannyml.acme.org/explore?${model_name:queryparam}﻿&${feature_names:queryparam}"
            }
          ],
          "mappings": [],
          "thresholds": {
            "mode": "absolute",
            "steps": [
              {
                "color": "green",
                "value": null
              },
              {
                "color": "red",
                "value": 0
              }
            ]
          }
        },
        "overrides": []
      },
      "gridPos": {
        "h": 6,
        "w": 4,
        "x": 0,
        "y": 0
      },
      "id": 18,
      "options": {
        "colorMode": "value",
        "graphMode": "area",
        "justifyMode": "auto",
        "orientation": "auto",
        "reduceOptions": {
          "calcs": [
            "sum"
          ],
          "fields": "/^alert$/",
          "values": false
        },
        "textMode": "auto"
      },
      "pluginVersion": "9.1.6",
      "targets": [
        {
          "datasource": {
            "type": "postgres",
            "uid": "te-11s7Vk"
          },
          "format": "time_series",
          "group": [
            {
              "params": [
                "$__interval",
                "none"
              ],
              "type": "time"
            }
          ],
          "metricColumn": "none",
          "rawQuery": true,
          "rawSql": "SELECT\n  $__timeGroupAlias(\"timestamp\",$__interval),\n  count(*) FILTER (WHERE alert) AS \"alert\"\nFROM statistical_feature_drift_metrics\nWHERE\n  $__timeFilter(\"timestamp\") AND\n  model_id = $model_id AND\n  feature_name IN ($feature_names)\nGROUP BY 1\nORDER BY 1",
          "refId": "A",
          "select": [
            [
              {
                "params": [
                  "alert"
                ],
                "type": "column"
              },
              {
                "params": [
                  "count"
                ],
                "type": "aggregate"
              },
              {
                "params": [
                  "alert"
                ],
                "type": "alias"
              }
            ]
          ],
          "table": "statistical_feature_drift_metrics",
          "timeColumn": "\"timestamp\"",
          "timeColumnType": "timestamp",
          "where": [
            {
              "name": "$__timeFilter",
              "params": [],
              "type": "macro"
            },
            {
              "datatype": "int4",
              "name": "",
              "params": [
                "model_id",
                "=",
                "$model_id"
              ],
              "type": "expression"
            },
            {
              "datatype": "varchar",
              "name": "",
              "params": [
                "feature_name",
                "IN",
                "($feature_names)"
              ],
              "type": "expression"
            }
          ]
        }
      ],
      "title": "Statistical Feature Drift Alerts",
      "type": "stat"
    },
    {
      "datasource": {
        "type": "postgres",
        "uid": "te-11s7Vk"
      },
      "description": "",
      "fieldConfig": {
        "defaults": {
          "color": {
            "mode": "thresholds"
          },
          "mappings": [],
          "thresholds": {
            "mode": "absolute",
            "steps": [
              {
                "color": "green",
                "value": null
              },
              {
                "color": "red",
                "value": 0
              }
            ]
          }
        },
        "overrides": []
      },
      "gridPos": {
        "h": 6,
        "w": 4,
        "x": 5,
        "y": 0
      },
      "id": 19,
      "options": {
        "colorMode": "value",
        "graphMode": "area",
        "justifyMode": "auto",
        "orientation": "auto",
        "reduceOptions": {
          "calcs": [
            "sum"
          ],
          "fields": "/^alert$/",
          "values": false
        },
        "textMode": "auto"
      },
      "pluginVersion": "9.1.6",
      "targets": [
        {
          "datasource": {
            "type": "postgres",
            "uid": "te-11s7Vk"
          },
          "format": "time_series",
          "group": [
            {
              "params": [
                "$__interval",
                "none"
              ],
              "type": "time"
            }
          ],
          "metricColumn": "none",
          "rawQuery": true,
          "rawSql": "SELECT\n  $__timeGroupAlias(\"timestamp\",$__interval),\n  count(*) FILTER (WHERE alert) AS \"alert\"\nFROM data_reconstruction_feature_drift_metrics\nWHERE\n  $__timeFilter(\"timestamp\") AND\n  model_id = $model_id\nGROUP BY 1\nORDER BY 1",
          "refId": "A",
          "select": [
            [
              {
                "params": [
                  "alert"
                ],
                "type": "column"
              },
              {
                "params": [
                  "count"
                ],
                "type": "aggregate"
              },
              {
                "params": [
                  "alert"
                ],
                "type": "alias"
              }
            ]
          ],
          "table": "statistical_feature_drift_metrics",
          "timeColumn": "\"timestamp\"",
          "timeColumnType": "timestamp",
          "where": [
            {
              "name": "$__timeFilter",
              "params": [],
              "type": "macro"
            },
            {
              "datatype": "int4",
              "name": "",
              "params": [
                "model_id",
                "=",
                "$model_id"
              ],
              "type": "expression"
            },
            {
              "datatype": "varchar",
              "name": "",
              "params": [
                "feature_name",
                "IN",
                "($feature_names)"
              ],
              "type": "expression"
            }
          ]
        }
      ],
      "title": "Reconstruction Error Drift Alerts",
      "type": "stat"
    },
    {
      "datasource": {
        "type": "postgres",
        "uid": "te-11s7Vk"
      },
      "description": "",
      "fieldConfig": {
        "defaults": {
          "color": {
            "mode": "thresholds"
          },
          "mappings": [],
          "thresholds": {
            "mode": "absolute",
            "steps": [
              {
                "color": "green",
                "value": null
              },
              {
                "color": "red",
                "value": 0
              }
            ]
          }
        },
        "overrides": []
      },
      "gridPos": {
        "h": 6,
        "w": 4,
        "x": 10,
        "y": 0
      },
      "id": 22,
      "options": {
        "colorMode": "value",
        "graphMode": "area",
        "justifyMode": "auto",
        "orientation": "auto",
        "reduceOptions": {
          "calcs": [
            "sum"
          ],
          "fields": "/^alert$/",
          "values": false
        },
        "textMode": "auto"
      },
      "pluginVersion": "9.1.6",
      "targets": [
        {
          "datasource": {
            "type": "postgres",
            "uid": "te-11s7Vk"
          },
          "format": "time_series",
          "group": [
            {
              "params": [
                "$__interval",
                "none"
              ],
              "type": "time"
            }
          ],
          "metricColumn": "none",
          "rawQuery": true,
          "rawSql": "SELECT\n  $__timeGroupAlias(\"timestamp\",$__interval),\n  count(*) FILTER (WHERE alert) AS \"alert\"\nFROM statistical_output_drift_metrics\nWHERE\n  $__timeFilter(\"timestamp\") AND\n  model_id = $model_id AND\n  output_name = 'y_pred'\nGROUP BY 1\nORDER BY 1",
          "refId": "A",
          "select": [
            [
              {
                "params": [
                  "alert"
                ],
                "type": "column"
              },
              {
                "params": [
                  "count"
                ],
                "type": "aggregate"
              },
              {
                "params": [
                  "alert"
                ],
                "type": "alias"
              }
            ]
          ],
          "table": "statistical_feature_drift_metrics",
          "timeColumn": "\"timestamp\"",
          "timeColumnType": "timestamp",
          "where": [
            {
              "name": "$__timeFilter",
              "params": [],
              "type": "macro"
            },
            {
              "datatype": "int4",
              "name": "",
              "params": [
                "model_id",
                "=",
                "$model_id"
              ],
              "type": "expression"
            },
            {
              "datatype": "varchar",
              "name": "",
              "params": [
                "feature_name",
                "IN",
                "($feature_names)"
              ],
              "type": "expression"
            }
          ]
        }
      ],
      "title": "Statistical Model Prediction Drift Alerts",
      "type": "stat"
    },
    {
      "datasource": {
        "type": "postgres",
        "uid": "te-11s7Vk"
      },
      "description": "",
      "fieldConfig": {
        "defaults": {
          "color": {
            "mode": "thresholds"
          },
          "mappings": [],
          "thresholds": {
            "mode": "absolute",
            "steps": [
              {
                "color": "green",
                "value": null
              },
              {
                "color": "red",
                "value": 0
              }
            ]
          }
        },
        "overrides": []
      },
      "gridPos": {
        "h": 6,
        "w": 4,
        "x": 15,
        "y": 0
      },
      "id": 20,
      "options": {
        "colorMode": "value",
        "graphMode": "area",
        "justifyMode": "auto",
        "orientation": "auto",
        "reduceOptions": {
          "calcs": [
            "sum"
          ],
          "fields": "/^alert$/",
          "values": false
        },
        "textMode": "auto"
      },
      "pluginVersion": "9.1.6",
      "targets": [
        {
          "datasource": {
            "type": "postgres",
            "uid": "te-11s7Vk"
          },
          "format": "time_series",
          "group": [
            {
              "params": [
                "$__interval",
                "none"
              ],
              "type": "time"
            }
          ],
          "metricColumn": "none",
          "rawQuery": true,
          "rawSql": "SELECT\n  $__timeGroupAlias(\"timestamp\",$__interval),\n  count(*) FILTER (WHERE alert) AS \"alert\"\nFROM statistical_output_drift_metrics\nWHERE\n  $__timeFilter(\"timestamp\") AND\n  model_id = $model_id AND\n  output_name = 'y_pred_proba'\nGROUP BY 1\nORDER BY 1",
          "refId": "A",
          "select": [
            [
              {
                "params": [
                  "alert"
                ],
                "type": "column"
              },
              {
                "params": [
                  "count"
                ],
                "type": "aggregate"
              },
              {
                "params": [
                  "alert"
                ],
                "type": "alias"
              }
            ]
          ],
          "table": "statistical_feature_drift_metrics",
          "timeColumn": "\"timestamp\"",
          "timeColumnType": "timestamp",
          "where": [
            {
              "name": "$__timeFilter",
              "params": [],
              "type": "macro"
            },
            {
              "datatype": "int4",
              "name": "",
              "params": [
                "model_id",
                "=",
                "$model_id"
              ],
              "type": "expression"
            },
            {
              "datatype": "varchar",
              "name": "",
              "params": [
                "feature_name",
                "IN",
                "($feature_names)"
              ],
              "type": "expression"
            }
          ]
        }
      ],
      "title": "Statistical Model Score Drift Alerts",
      "type": "stat"
    },
    {
      "datasource": {
        "type": "postgres",
        "uid": "te-11s7Vk"
      },
      "description": "",
      "fieldConfig": {
        "defaults": {
          "color": {
            "mode": "thresholds"
          },
          "mappings": [],
          "thresholds": {
            "mode": "absolute",
            "steps": [
              {
                "color": "green",
                "value": null
              },
              {
                "color": "red",
                "value": 0
              }
            ]
          }
        },
        "overrides": []
      },
      "gridPos": {
        "h": 6,
        "w": 4,
        "x": 20,
        "y": 0
      },
      "id": 23,
      "libraryPanel": {
        "uid": "px31f74Vk"
      },
      "options": {
        "colorMode": "value",
        "graphMode": "area",
        "justifyMode": "auto",
        "orientation": "auto",
        "reduceOptions": {
          "calcs": [
            "sum"
          ],
          "fields": "/^alert$/",
          "values": false
        },
        "textMode": "auto"
      },
      "pluginVersion": "9.1.6",
      "targets": [
        {
          "datasource": {
            "type": "postgres",
            "uid": "te-11s7Vk"
          },
          "format": "time_series",
          "group": [
            {
              "params": [
                "$__interval",
                "none"
              ],
              "type": "time"
            }
          ],
          "metricColumn": "none",
          "rawQuery": true,
          "rawSql": "SELECT\n  $__timeGroupAlias(\"timestamp\",$__interval),\n  count(*) FILTER (WHERE alert) AS \"alert\"\nFROM target_drift_metrics\nWHERE\n  $__timeFilter(\"timestamp\") AND\n  model_id = $model_id\nGROUP BY 1\nORDER BY 1",
          "refId": "A",
          "select": [
            [
              {
                "params": [
                  "alert"
                ],
                "type": "column"
              },
              {
                "params": [
                  "count"
                ],
                "type": "aggregate"
              },
              {
                "params": [
                  "alert"
                ],
                "type": "alias"
              }
            ]
          ],
          "table": "statistical_feature_drift_metrics",
          "timeColumn": "\"timestamp\"",
          "timeColumnType": "timestamp",
          "where": [
            {
              "name": "$__timeFilter",
              "params": [],
              "type": "macro"
            },
            {
              "datatype": "int4",
              "name": "",
              "params": [
                "model_id",
                "=",
                "$model_id"
              ],
              "type": "expression"
            },
            {
              "datatype": "varchar",
              "name": "",
              "params": [
                "feature_name",
                "IN",
                "($feature_names)"
              ],
              "type": "expression"
            }
          ]
        }
      ],
      "title": "Statistical Target Drift Alerts",
      "type": "stat"
    },
    {
      "collapsed": false,
      "gridPos": {
        "h": 1,
        "w": 24,
        "x": 0,
        "y": 6
      },
      "id": 9,
      "panels": [],
      "title": "Model inputs",
      "type": "row"
    },
    {
      "datasource": {
        "type": "postgres",
        "uid": "te-11s7Vk"
      },
      "description": "",
      "fieldConfig": {
        "defaults": {
          "color": {
            "mode": "palette-classic",
            "seriesBy": "min"
          },
          "custom": {
            "axisCenteredZero": false,
            "axisColorMode": "text",
            "axisLabel": "",
            "axisPlacement": "auto",
            "barAlignment": 0,
            "drawStyle": "line",
            "fillOpacity": 0,
            "gradientMode": "none",
            "hideFrom": {
              "legend": false,
              "tooltip": false,
              "viz": false
            },
            "lineInterpolation": "linear",
            "lineWidth": 1,
            "pointSize": 5,
            "scaleDistribution": {
              "type": "linear"
            },
            "showPoints": "auto",
            "spanNulls": false,
            "stacking": {
              "group": "A",
              "mode": "none"
            },
            "thresholdsStyle": {
              "mode": "line"
            }
          },
          "mappings": [],
          "thresholds": {
            "mode": "absolute",
            "steps": [
              {
                "color": "green",
                "value": null
              }
            ]
          }
        },
        "overrides": [
          {
            "matcher": {
              "id": "byFrameRefID",
              "options": "B"
            },
            "properties": [
              {
                "id": "custom.drawStyle",
                "value": "bars"
              },
              {
                "id": "custom.fillOpacity",
                "value": 40
              },
              {
                "id": "custom.lineStyle",
                "value": {
                  "dash": [
                    10,
                    10
                  ],
                  "fill": "dash"
                }
              },
              {
                "id": "custom.barAlignment",
                "value": 0
              },
              {
                "id": "color",
                "value": {
                  "fixedColor": "red",
                  "mode": "fixed"
                }
              }
            ]
          }
        ]
      },
      "gridPos": {
        "h": 8,
        "w": 12,
        "x": 0,
        "y": 7
      },
      "id": 16,
      "options": {
        "legend": {
          "calcs": [],
          "displayMode": "list",
          "placement": "bottom",
          "showLegend": true
        },
        "tooltip": {
          "mode": "single",
          "sort": "none"
        }
      },
      "targets": [
        {
          "datasource": {
            "type": "postgres",
            "uid": "te-11s7Vk"
          },
          "format": "time_series",
          "group": [],
          "hide": false,
          "metricColumn": "metric_name",
          "rawQuery": false,
          "rawSql": "SELECT\n  \"timestamp\" AS \"time\",\n  metric_name AS metric,\n  value,\n  feature_name\nFROM statistical_feature_drift_metrics\nWHERE\n  $__timeFilter(\"timestamp\") AND\n  model_id = $model_id AND\n  feature_name IN ($feature_names)\nORDER BY 1,2",
          "refId": "A",
          "select": [
            [
              {
                "params": [
                  "value"
                ],
                "type": "column"
              }
            ],
            [
              {
                "params": [
                  "feature_name"
                ],
                "type": "column"
              }
            ]
          ],
          "table": "statistical_feature_drift_metrics",
          "timeColumn": "\"timestamp\"",
          "timeColumnType": "timestamp",
          "where": [
            {
              "name": "$__timeFilter",
              "params": [],
              "type": "macro"
            },
            {
              "datatype": "int4",
              "name": "",
              "params": [
                "model_id",
                "=",
                "$model_id"
              ],
              "type": "expression"
            },
            {
              "datatype": "varchar",
              "name": "",
              "params": [
                "feature_name",
                "IN",
                "($feature_names)"
              ],
              "type": "expression"
            }
          ]
        },
        {
          "datasource": {
            "type": "postgres",
            "uid": "te-11s7Vk"
          },
          "format": "table",
          "group": [],
          "hide": false,
          "metricColumn": "none",
          "rawQuery": false,
          "rawSql": "SELECT\n  \"timestamp\" AS \"time\",\n  alert\nFROM statistical_feature_drift_metrics\nWHERE\n  $__timeFilter(\"timestamp\") AND\n  model_id = $model_id AND\n  feature_name IN ($feature_names)\nORDER BY 1",
          "refId": "B",
          "select": [
            [
              {
                "params": [
                  "alert"
                ],
                "type": "column"
              }
            ]
          ],
          "table": "statistical_feature_drift_metrics",
          "timeColumn": "\"timestamp\"",
          "timeColumnType": "timestamp",
          "where": [
            {
              "name": "$__timeFilter",
              "params": [],
              "type": "macro"
            },
            {
              "datatype": "int4",
              "name": "",
              "params": [
                "model_id",
                "=",
                "$model_id"
              ],
              "type": "expression"
            },
            {
              "datatype": "varchar",
              "name": "",
              "params": [
                "feature_name",
                "IN",
                "($feature_names)"
              ],
              "type": "expression"
            }
          ]
        }
      ],
      "title": "Univariate Feature Drift: ${feature_names}",
      "transformations": [
        {
          "id": "configFromData",
          "options": {}
        }
      ],
      "type": "timeseries"
    },
    {
      "datasource": {
        "type": "postgres",
        "uid": "te-11s7Vk"
      },
      "fieldConfig": {
        "defaults": {
          "color": {
            "mode": "palette-classic",
            "seriesBy": "last"
          },
          "custom": {
            "axisCenteredZero": false,
            "axisColorMode": "text",
            "axisLabel": "",
            "axisPlacement": "auto",
            "barAlignment": 0,
            "drawStyle": "line",
            "fillOpacity": 0,
            "gradientMode": "none",
            "hideFrom": {
              "legend": false,
              "tooltip": false,
              "viz": false
            },
            "lineInterpolation": "linear",
            "lineWidth": 1,
            "pointSize": 5,
            "scaleDistribution": {
              "type": "linear"
            },
            "showPoints": "auto",
            "spanNulls": false,
            "stacking": {
              "group": "A",
              "mode": "none"
            },
            "thresholdsStyle": {
              "mode": "line"
            }
          },
          "mappings": [],
          "thresholds": {
            "mode": "absolute",
            "steps": [
              {
                "color": "green",
                "value": null
              }
            ]
          }
        },
        "overrides": [
          {
            "matcher": {
              "id": "byFrameRefID",
              "options": "Alerts"
            },
            "properties": [
              {
                "id": "custom.drawStyle",
                "value": "bars"
              },
              {
                "id": "custom.fillOpacity",
                "value": 25
              },
              {
                "id": "custom.pointSize",
                "value": 10
              },
              {
                "id": "custom.barAlignment",
                "value": 0
              },
              {
                "id": "custom.lineStyle",
                "value": {
                  "dash": [
                    10,
                    10
                  ],
                  "fill": "dash"
                }
              },
              {
                "id": "color",
                "value": {
                  "fixedColor": "red",
                  "mode": "fixed"
                }
              }
            ]
          },
          {
            "matcher": {
              "id": "byFrameRefID",
              "options": "Thresholds"
            },
            "properties": [
              {
                "id": "custom.showPoints",
                "value": "never"
              }
            ]
          }
        ]
      },
      "gridPos": {
        "h": 8,
        "w": 12,
        "x": 12,
        "y": 7
      },
      "id": 4,
      "options": {
        "legend": {
          "calcs": [],
          "displayMode": "list",
          "placement": "bottom",
          "showLegend": true
        },
        "tooltip": {
          "mode": "single",
          "sort": "none"
        }
      },
      "targets": [
        {
          "datasource": {
            "type": "postgres",
            "uid": "te-11s7Vk"
          },
          "format": "time_series",
          "group": [],
          "metricColumn": "metric_name",
          "rawQuery": false,
          "rawSql": "SELECT\n  \"timestamp\" AS \"time\",\n  metric_name AS metric,\n  value\nFROM data_reconstruction_feature_drift_metrics\nWHERE\n  $__timeFilter(\"timestamp\") AND\n  model_id = $model_id\nORDER BY 1,2",
          "refId": "Values",
          "select": [
            [
              {
                "params": [
                  "value"
                ],
                "type": "column"
              }
            ]
          ],
          "table": "data_reconstruction_feature_drift_metrics",
          "timeColumn": "\"timestamp\"",
          "timeColumnType": "timestamp",
          "where": [
            {
              "name": "$__timeFilter",
              "params": [],
              "type": "macro"
            },
            {
              "datatype": "int4",
              "name": "",
              "params": [
                "model_id",
                "=",
                "$model_id"
              ],
              "type": "expression"
            }
          ]
        },
        {
          "datasource": {
            "type": "postgres",
            "uid": "te-11s7Vk"
          },
          "format": "time_series",
          "group": [],
          "hide": false,
          "metricColumn": "none",
          "rawQuery": false,
          "rawSql": "SELECT\n  \"timestamp\" AS \"time\",\n  lower_threshold,\n  upper_threshold\nFROM data_reconstruction_feature_drift_metrics\nWHERE\n  $__timeFilter(\"timestamp\") AND\n  model_id = $model_id\nORDER BY 1",
          "refId": "Thresholds",
          "select": [
            [
              {
                "params": [
                  "lower_threshold"
                ],
                "type": "column"
              }
            ],
            [
              {
                "params": [
                  "upper_threshold"
                ],
                "type": "column"
              }
            ]
          ],
          "table": "data_reconstruction_feature_drift_metrics",
          "timeColumn": "\"timestamp\"",
          "timeColumnType": "timestamp",
          "where": [
            {
              "name": "$__timeFilter",
              "params": [],
              "type": "macro"
            },
            {
              "datatype": "int4",
              "name": "",
              "params": [
                "model_id",
                "=",
                "$model_id"
              ],
              "type": "expression"
            }
          ]
        },
        {
          "datasource": {
            "type": "postgres",
            "uid": "te-11s7Vk"
          },
          "format": "table",
          "group": [],
          "hide": false,
          "metricColumn": "none",
          "rawQuery": false,
          "rawSql": "SELECT\n  \"timestamp\" AS \"time\",\n  alert\nFROM data_reconstruction_feature_drift_metrics\nWHERE\n  $__timeFilter(\"timestamp\") AND\n  model_id = $model_id\nORDER BY 1",
          "refId": "Alerts",
          "select": [
            [
              {
                "params": [
                  "alert"
                ],
                "type": "column"
              }
            ]
          ],
          "table": "data_reconstruction_feature_drift_metrics",
          "timeColumn": "\"timestamp\"",
          "timeColumnType": "timestamp",
          "where": [
            {
              "name": "$__timeFilter",
              "params": [],
              "type": "macro"
            },
            {
              "datatype": "int4",
              "name": "",
              "params": [
                "model_id",
                "=",
                "$model_id"
              ],
              "type": "expression"
            }
          ]
        }
      ],
      "title": "Multivariate Drift - Reconstruction Error (PCA)",
      "transformations": [],
      "type": "timeseries"
    },
    {
      "collapsed": false,
      "gridPos": {
        "h": 1,
        "w": 24,
        "x": 0,
        "y": 15
      },
      "id": 11,
      "panels": [],
      "title": "Model outputs",
      "type": "row"
    },
    {
      "datasource": {
        "type": "postgres",
        "uid": "te-11s7Vk"
      },
      "fieldConfig": {
        "defaults": {
          "color": {
            "mode": "palette-classic"
          },
          "custom": {
            "axisCenteredZero": false,
            "axisColorMode": "text",
            "axisLabel": "",
            "axisPlacement": "auto",
            "barAlignment": 0,
            "drawStyle": "line",
            "fillOpacity": 0,
            "gradientMode": "none",
            "hideFrom": {
              "legend": false,
              "tooltip": false,
              "viz": false
            },
            "lineInterpolation": "linear",
            "lineWidth": 1,
            "pointSize": 5,
            "scaleDistribution": {
              "type": "linear"
            },
            "showPoints": "auto",
            "spanNulls": false,
            "stacking": {
              "group": "A",
              "mode": "none"
            },
            "thresholdsStyle": {
              "mode": "off"
            }
          },
          "mappings": [],
          "thresholds": {
            "mode": "absolute",
            "steps": [
              {
                "color": "green",
                "value": null
              },
              {
                "color": "red",
                "value": 80
              }
            ]
          }
        },
        "overrides": [
          {
            "matcher": {
              "id": "byFrameRefID",
              "options": "B"
            },
            "properties": [
              {
                "id": "custom.drawStyle",
                "value": "bars"
              },
              {
                "id": "custom.barAlignment",
                "value": 0
              },
              {
                "id": "custom.lineStyle",
                "value": {
                  "dash": [
                    10,
                    10
                  ],
                  "fill": "dash"
                }
              },
              {
                "id": "custom.fillOpacity",
                "value": 40
              },
              {
                "id": "color",
                "value": {
                  "fixedColor": "red",
                  "mode": "fixed"
                }
              }
            ]
          }
        ]
      },
      "gridPos": {
        "h": 8,
        "w": 12,
        "x": 0,
        "y": 16
      },
      "id": 6,
      "options": {
        "legend": {
          "calcs": [],
          "displayMode": "list",
          "placement": "bottom",
          "showLegend": true
        },
        "tooltip": {
          "mode": "single",
          "sort": "none"
        }
      },
      "targets": [
        {
          "datasource": {
            "type": "postgres",
            "uid": "te-11s7Vk"
          },
          "format": "time_series",
          "group": [],
          "metricColumn": "metric_name",
          "rawQuery": false,
          "rawSql": "SELECT\n  \"timestamp\" AS \"time\",\n  metric_name AS metric,\n  value\nFROM statistical_output_drift_metrics\nWHERE\n  $__timeFilter(\"timestamp\") AND\n  model_id = $model_id AND\n  output_name = 'y_pred'\nORDER BY 1,2",
          "refId": "A",
          "select": [
            [
              {
                "params": [
                  "value"
                ],
                "type": "column"
              }
            ]
          ],
          "table": "statistical_output_drift_metrics",
          "timeColumn": "\"timestamp\"",
          "timeColumnType": "timestamp",
          "where": [
            {
              "name": "$__timeFilter",
              "params": [],
              "type": "macro"
            },
            {
              "datatype": "int4",
              "name": "",
              "params": [
                "model_id",
                "=",
                "$model_id"
              ],
              "type": "expression"
            },
            {
              "datatype": "varchar",
              "name": "",
              "params": [
                "output_name",
                "=",
                "'y_pred'"
              ],
              "type": "expression"
            }
          ]
        },
        {
          "datasource": {
            "type": "postgres",
            "uid": "te-11s7Vk"
          },
          "format": "table",
          "group": [],
          "hide": false,
          "metricColumn": "none",
          "rawQuery": false,
          "rawSql": "SELECT\n  \"timestamp\" AS \"time\",\n  alert\nFROM statistical_output_drift_metrics\nWHERE\n  $__timeFilter(\"timestamp\") AND\n  model_id = $model_id AND\n  output_name = 'y_pred'\nORDER BY 1",
          "refId": "B",
          "select": [
            [
              {
                "params": [
                  "alert"
                ],
                "type": "column"
              }
            ]
          ],
          "table": "statistical_output_drift_metrics",
          "timeColumn": "\"timestamp\"",
          "timeColumnType": "timestamp",
          "where": [
            {
              "name": "$__timeFilter",
              "params": [],
              "type": "macro"
            },
            {
              "datatype": "int4",
              "name": "",
              "params": [
                "model_id",
                "=",
                "$model_id"
              ],
              "type": "expression"
            },
            {
              "datatype": "varchar",
              "name": "",
              "params": [
                "output_name",
                "=",
                "'y_pred'"
              ],
              "type": "expression"
            }
          ]
        }
      ],
      "title": "Prediction Drift",
      "type": "timeseries"
    },
    {
      "datasource": {
        "type": "postgres",
        "uid": "te-11s7Vk"
      },
      "fieldConfig": {
        "defaults": {
          "color": {
            "mode": "palette-classic"
          },
          "custom": {
            "axisCenteredZero": false,
            "axisColorMode": "text",
            "axisLabel": "",
            "axisPlacement": "auto",
            "barAlignment": 0,
            "drawStyle": "line",
            "fillOpacity": 0,
            "gradientMode": "none",
            "hideFrom": {
              "legend": false,
              "tooltip": false,
              "viz": false
            },
            "lineInterpolation": "linear",
            "lineWidth": 1,
            "pointSize": 5,
            "scaleDistribution": {
              "type": "linear"
            },
            "showPoints": "auto",
            "spanNulls": false,
            "stacking": {
              "group": "A",
              "mode": "none"
            },
            "thresholdsStyle": {
              "mode": "off"
            }
          },
          "mappings": [],
          "thresholds": {
            "mode": "absolute",
            "steps": [
              {
                "color": "green",
                "value": null
              }
            ]
          }
        },
        "overrides": [
          {
            "matcher": {
              "id": "byFrameRefID",
              "options": "B"
            },
            "properties": [
              {
                "id": "custom.drawStyle",
                "value": "bars"
              },
              {
                "id": "custom.fillOpacity",
                "value": 40
              },
              {
                "id": "custom.lineStyle",
                "value": {
                  "dash": [
                    10,
                    10
                  ],
                  "fill": "dash"
                }
              },
              {
                "id": "color",
                "value": {
                  "fixedColor": "red",
                  "mode": "fixed"
                }
              }
            ]
          }
        ]
      },
      "gridPos": {
        "h": 8,
        "w": 12,
        "x": 12,
        "y": 16
      },
      "id": 7,
      "options": {
        "legend": {
          "calcs": [],
          "displayMode": "list",
          "placement": "bottom",
          "showLegend": true
        },
        "tooltip": {
          "mode": "single",
          "sort": "none"
        }
      },
      "targets": [
        {
          "datasource": {
            "type": "postgres",
            "uid": "te-11s7Vk"
          },
          "format": "time_series",
          "group": [],
          "metricColumn": "metric_name",
          "rawQuery": true,
          "rawSql": "SELECT\n  \"timestamp\" AS \"time\",\n  concat(metric_name, ' - ', 'Upmarket Card') AS metric,\n  value\nFROM statistical_output_drift_metrics\nWHERE\n  $__timeFilter(\"timestamp\") AND\n  model_id = $model_id AND\n  output_name = 'y_pred_proba_upmarket_card'\nORDER BY 1,2",
          "refId": "A",
          "select": [
            [
              {
                "params": [
                  "value"
                ],
                "type": "column"
              }
            ]
          ],
          "table": "statistical_output_drift_metrics",
          "timeColumn": "\"timestamp\"",
          "timeColumnType": "timestamp",
          "where": [
            {
              "name": "$__timeFilter",
              "params": [],
              "type": "macro"
            },
            {
              "datatype": "int4",
              "name": "",
              "params": [
                "model_id",
                "=",
                "$model_id"
              ],
              "type": "expression"
            },
            {
              "datatype": "varchar",
              "name": "",
              "params": [
                "output_name",
                "=",
                "'y_pred_proba_upmarket_card'"
              ],
              "type": "expression"
            }
          ]
        },
        {
          "datasource": {
            "type": "postgres",
            "uid": "te-11s7Vk"
          },
          "format": "table",
          "group": [],
          "hide": false,
          "metricColumn": "none",
          "rawQuery": false,
          "rawSql": "SELECT\n  \"timestamp\" AS \"time\",\n  alert\nFROM statistical_output_drift_metrics\nWHERE\n  $__timeFilter(\"timestamp\") AND\n  model_id = $model_id AND\n  output_name = 'y_pred_proba'\nORDER BY 1",
          "refId": "B",
          "select": [
            [
              {
                "params": [
                  "alert"
                ],
                "type": "column"
              }
            ]
          ],
          "table": "statistical_output_drift_metrics",
          "timeColumn": "\"timestamp\"",
          "timeColumnType": "timestamp",
          "where": [
            {
              "name": "$__timeFilter",
              "params": [],
              "type": "macro"
            },
            {
              "datatype": "int4",
              "name": "",
              "params": [
                "model_id",
                "=",
                "$model_id"
              ],
              "type": "expression"
            },
            {
              "datatype": "varchar",
              "name": "",
              "params": [
                "output_name",
                "=",
                "'y_pred_proba'"
              ],
              "type": "expression"
            }
          ]
        },
        {
          "datasource": {
            "type": "postgres",
            "uid": "te-11s7Vk"
          },
          "format": "time_series",
          "group": [],
          "hide": false,
          "metricColumn": "metric_name",
          "rawQuery": true,
          "rawSql": "SELECT\n  \"timestamp\" AS \"time\",\n  concat(metric_name, ' - ', 'Highstreet Card') AS metric,\n  value\nFROM statistical_output_drift_metrics\nWHERE\n  $__timeFilter(\"timestamp\") AND\n  model_id = $model_id AND\n  output_name = 'y_pred_proba_highstreet_card'\nORDER BY 1,2",
          "refId": "C",
          "select": [
            [
              {
                "params": [
                  "value"
                ],
                "type": "column"
              }
            ]
          ],
          "table": "statistical_output_drift_metrics",
          "timeColumn": "\"timestamp\"",
          "timeColumnType": "timestamp",
          "where": [
            {
              "name": "$__timeFilter",
              "params": [],
              "type": "macro"
            },
            {
              "datatype": "int4",
              "name": "",
              "params": [
                "model_id",
                "=",
                "$model_id"
              ],
              "type": "expression"
            },
            {
              "datatype": "varchar",
              "name": "",
              "params": [
                "output_name",
                "=",
                "'y_pred_proba_highstreet_card'"
              ],
              "type": "expression"
            }
          ]
        },
        {
          "datasource": {
            "type": "postgres",
            "uid": "te-11s7Vk"
          },
          "format": "time_series",
          "group": [],
          "hide": false,
          "metricColumn": "metric_name",
          "rawQuery": true,
          "rawSql": "SELECT\n  \"timestamp\" AS \"time\",\n  concat(metric_name, ' - ', 'Prepaid Card') AS metric,\n  value\nFROM statistical_output_drift_metrics\nWHERE\n  $__timeFilter(\"timestamp\") AND\n  model_id = $model_id AND\n  output_name = 'y_pred_proba_prepaid_card'\nORDER BY 1,2",
          "refId": "D",
          "select": [
            [
              {
                "params": [
                  "value"
                ],
                "type": "column"
              }
            ]
          ],
          "table": "statistical_output_drift_metrics",
          "timeColumn": "\"timestamp\"",
          "timeColumnType": "timestamp",
          "where": [
            {
              "name": "$__timeFilter",
              "params": [],
              "type": "macro"
            },
            {
              "datatype": "int4",
              "name": "",
              "params": [
                "model_id",
                "=",
                "$model_id"
              ],
              "type": "expression"
            },
            {
              "datatype": "varchar",
              "name": "",
              "params": [
                "output_name",
                "=",
                "'y_pred_proba_prepaid_card'"
              ],
              "type": "expression"
            }
          ]
        }
      ],
      "title": "Score Drift",
      "type": "timeseries"
    },
    {
      "collapsed": false,
      "gridPos": {
        "h": 1,
        "w": 24,
        "x": 0,
        "y": 24
      },
      "id": 13,
      "panels": [],
      "title": "Model targets",
      "type": "row"
    },
    {
      "datasource": {
        "type": "postgres",
        "uid": "te-11s7Vk"
      },
      "fieldConfig": {
        "defaults": {
          "color": {
            "mode": "palette-classic"
          },
          "custom": {
            "axisCenteredZero": false,
            "axisColorMode": "text",
            "axisLabel": "",
            "axisPlacement": "auto",
            "barAlignment": 0,
            "drawStyle": "line",
            "fillOpacity": 0,
            "gradientMode": "none",
            "hideFrom": {
              "legend": false,
              "tooltip": false,
              "viz": false
            },
            "lineInterpolation": "linear",
            "lineWidth": 1,
            "pointSize": 5,
            "scaleDistribution": {
              "type": "linear"
            },
            "showPoints": "auto",
            "spanNulls": false,
            "stacking": {
              "group": "A",
              "mode": "none"
            },
            "thresholdsStyle": {
              "mode": "off"
            }
          },
          "mappings": [],
          "thresholds": {
            "mode": "absolute",
            "steps": [
              {
                "color": "green",
                "value": null
              },
              {
                "color": "red",
                "value": 80
              }
            ]
          }
        },
        "overrides": [
          {
            "matcher": {
              "id": "byFrameRefID",
              "options": "B"
            },
            "properties": [
              {
                "id": "custom.drawStyle",
                "value": "bars"
              },
              {
                "id": "custom.fillOpacity",
                "value": 40
              },
              {
                "id": "custom.lineStyle",
                "value": {
                  "dash": [
                    10,
                    10
                  ],
                  "fill": "dash"
                }
              },
              {
                "id": "color",
                "value": {
                  "fixedColor": "red",
                  "mode": "fixed"
                }
              }
            ]
          }
        ]
      },
      "gridPos": {
        "h": 8,
        "w": 12,
        "x": 0,
        "y": 25
      },
      "id": 15,
      "options": {
        "legend": {
          "calcs": [],
          "displayMode": "list",
          "placement": "bottom",
          "showLegend": true
        },
        "tooltip": {
          "mode": "single",
          "sort": "none"
        }
      },
      "targets": [
        {
          "datasource": {
            "type": "postgres",
            "uid": "te-11s7Vk"
          },
          "format": "time_series",
          "group": [],
          "metricColumn": "metric_name",
          "rawQuery": false,
          "rawSql": "SELECT\n  \"timestamp\" AS \"time\",\n  metric_name AS metric,\n  value\nFROM target_drift_metrics\nWHERE\n  $__timeFilter(\"timestamp\") AND\n  model_id = $model_id\nORDER BY 1,2",
          "refId": "A",
          "select": [
            [
              {
                "params": [
                  "value"
                ],
                "type": "column"
              }
            ]
          ],
          "table": "target_drift_metrics",
          "timeColumn": "\"timestamp\"",
          "timeColumnType": "timestamp",
          "where": [
            {
              "name": "$__timeFilter",
              "params": [],
              "type": "macro"
            },
            {
              "datatype": "int4",
              "name": "",
              "params": [
                "model_id",
                "=",
                "$model_id"
              ],
              "type": "expression"
            }
          ]
        },
        {
          "datasource": {
            "type": "postgres",
            "uid": "te-11s7Vk"
          },
          "format": "table",
          "group": [],
          "hide": false,
          "metricColumn": "none",
          "rawQuery": false,
          "rawSql": "SELECT\n  \"timestamp\" AS \"time\",\n  alert\nFROM target_drift_metrics\nWHERE\n  $__timeFilter(\"timestamp\") AND\n  model_id = $model_id\nORDER BY 1",
          "refId": "B",
          "select": [
            [
              {
                "params": [
                  "alert"
                ],
                "type": "column"
              }
            ]
          ],
          "table": "target_drift_metrics",
          "timeColumn": "\"timestamp\"",
          "timeColumnType": "timestamp",
          "where": [
            {
              "name": "$__timeFilter",
              "params": [],
              "type": "macro"
            },
            {
              "datatype": "int4",
              "name": "",
              "params": [
                "model_id",
                "=",
                "$model_id"
              ],
              "type": "expression"
            }
          ]
        }
      ],
      "title": "Target Drift",
      "type": "timeseries"
    }
  ],
  "refresh": false,
  "schemaVersion": 37,
  "style": "dark",
  "tags": [],
  "templating": {
    "list": [
      {
        "current": {
          "selected": true,
          "text": "credit_card_classification",
          "value": "credit_card_classification"
        },
        "datasource": {
          "type": "postgres",
          "uid": "te-11s7Vk"
        },
        "definition": "select distinct name from model",
        "hide": 0,
        "includeAll": false,
        "label": "Model",
        "multi": false,
        "name": "model_name",
        "options": [],
        "query": "select distinct name from model",
        "refresh": 1,
        "regex": "",
        "skipUrlSync": false,
        "sort": 0,
        "type": "query"
      },
      {
        "current": {
          "selected": false,
          "text": "1",
          "value": "1"
        },
        "datasource": {
          "type": "postgres",
          "uid": "te-11s7Vk"
        },
        "definition": "select id from model where model.name = '${model_name}'",
        "hide": 2,
        "includeAll": false,
        "multi": false,
        "name": "model_id",
        "options": [],
        "query": "select id from model where model.name = '${model_name}'",
        "refresh": 1,
        "regex": "",
        "skipUrlSync": false,
        "sort": 0,
        "type": "query"
      },
      {
        "current": {
          "selected": false,
          "text": "acq_channel",
          "value": "acq_channel"
        },
        "datasource": {
          "type": "postgres",
          "uid": "te-11s7Vk"
        },
        "definition": "select distinct feature_name from statistical_feature_drift_metrics  where model_id=${model_id}",
        "hide": 0,
        "includeAll": false,
        "label": "Features",
        "multi": true,
        "name": "feature_names",
        "options": [],
        "query": "select distinct feature_name from statistical_feature_drift_metrics  where model_id=${model_id}",
        "refresh": 1,
        "regex": "",
        "skipUrlSync": false,
        "sort": 1,
        "type": "query"
      }
    ]
  },
  "time": {
    "from": "2020-08-10T12:27:59.596Z",
    "to": "2020-11-08T12:05:07.663Z"
  },
  "timepicker": {},
  "timezone": "",
  "title": "Drift",
  "uid": "ugSEbsnVz2",
  "version": 7,
  "weekStart": "monday"
}
